agentastic/__init__.py
agentastic-0.0.3.dist-info/METADATA
agentastic-0.0.3.dist-info/WHEEL
agentastic-0.0.3.dist-info/top_level.txt
agentastic-0.0.3.dist-info/RECORD
